streamlit_js/__init__.py
streamlit_js/frontend/build/asset-manifest.json
streamlit_js/frontend/build/bootstrap.min.css
streamlit_js/frontend/build/bootstrap.min.css.map
streamlit_js/frontend/build/index.html
streamlit_js/frontend/build/static/js/main.27043a48.js
streamlit_js/frontend/build/static/js/main.27043a48.js.LICENSE.txt
streamlit_js/frontend/build/static/js/main.27043a48.js.map
streamlit_js/frontend/build/static/js/main.34c58eda.js
streamlit_js/frontend/build/static/js/main.34c58eda.js.LICENSE.txt
streamlit_js/frontend/build/static/js/main.34c58eda.js.map
streamlit_js/frontend/build/static/js/main.53d6ba46.js
streamlit_js/frontend/build/static/js/main.53d6ba46.js.LICENSE.txt
streamlit_js/frontend/build/static/js/main.53d6ba46.js.map
streamlit_js/frontend/build/static/js/main.ca97769c.js
streamlit_js/frontend/build/static/js/main.ca97769c.js.LICENSE.txt
streamlit_js/frontend/build/static/js/main.ca97769c.js.map
streamlit_js-1.0.8.dist-info/LICENSE
streamlit_js-1.0.8.dist-info/METADATA
streamlit_js-1.0.8.dist-info/WHEEL
streamlit_js-1.0.8.dist-info/top_level.txt
streamlit_js-1.0.8.dist-info/RECORD
