Metadata-Version: 2.1
Name: streamlit-js
Version: 1.0.8
Summary: Streamlit component that allows you to run js code with both blocking and non-blocking modes.
Home-page: https://github.com/toolittlecakes/streamlit_js
Author: Nikolay Sheyko
Author-email: nickolay.sheyko@gmail.com.com
Requires-Python: >=3.7
License-File: LICENSE
Requires-Dist: streamlit >=0.63
Provides-Extra: devel
Requires-Dist: wheel ; extra == 'devel'
Requires-Dist: pytest ==7.4.0 ; extra == 'devel'
Requires-Dist: playwright ==1.39.0 ; extra == 'devel'
Requires-Dist: requests ==2.31.0 ; extra == 'devel'
Requires-Dist: pytest-playwright-snapshot ==1.0 ; extra == 'devel'
Requires-Dist: pytest-rerunfailures ==12.0 ; extra == 'devel'
